<processor>

<register>
<number>1</number>
<name>PC</name>
<bits>8</bits>
<xcoordinate>159</xcoordinate>
<ycoordinate>129</ycoordinate>
</register>

<memory>
<number>2</number>
<name>memory</name>
<bits>8</bits>
<xcoordinate>252</xcoordinate>
<ycoordinate>224</ycoordinate>
</memory>

<adder>
<number>3</number>
<name></name>
<bits>8</bits>
<xcoordinate>139</xcoordinate>
<ycoordinate>249</ycoordinate>
</adder>

<constant>
<number>4</number>
<name>1</name>
<bits>8</bits>
<xcoordinate>135</xcoordinate>
<ycoordinate>173</ycoordinate>
</constant>

<register>
<number>5</number>
<name>value1</name>
<bits>8</bits>
<xcoordinate>283</xcoordinate>
<ycoordinate>318</ycoordinate>
</register>

<register>
<number>6</number>
<name>value2</name>
<bits>8</bits>
<xcoordinate>360</xcoordinate>
<ycoordinate>320</ycoordinate>
</register>

<register>
<number>7</number>
<name>sum</name>
<bits>8</bits>
<xcoordinate>319</xcoordinate>
<ycoordinate>469</ycoordinate>
</register>

<adder>
<number>8</number>
<name></name>
<bits>8</bits>
<xcoordinate>314</xcoordinate>
<ycoordinate>393</ycoordinate>
</adder>

<bus>
<number>9</number>
<name></name>
<bits>8</bits>
<xcoordinate>179</xcoordinate>
<ycoordinate>159</ycoordinate>
<xcoordinate2>179</xcoordinate2>
<ycoordinate2>237</ycoordinate2>
<entry>1</entry>
<exit>0</exit>
</bus>

<bus>
<number>10</number>
<name></name>
<bits>8</bits>
<xcoordinate>179</xcoordinate>
<ycoordinate>235</ycoordinate>
<xcoordinate2>166</xcoordinate2>
<ycoordinate2>235</ycoordinate2>
<entry>9</entry>
<exit>0</exit>
</bus>

<bus>
<number>11</number>
<name></name>
<bits>8</bits>
<xcoordinate>167</xcoordinate>
<ycoordinate>235</ycoordinate>
<xcoordinate2>167</xcoordinate2>
<ycoordinate2>249</ycoordinate2>
<entry>10</entry>
<exit>3</exit>
</bus>

<bus>
<number>12</number>
<name></name>
<bits>8</bits>
<xcoordinate>179</xcoordinate>
<ycoordinate>231</ycoordinate>
<xcoordinate2>252</xcoordinate2>
<ycoordinate2>231</ycoordinate2>
<entry>9</entry>
<exit>2</exit>
</bus>

<bus>
<number>13</number>
<name></name>
<bits>8</bits>
<xcoordinate>145</xcoordinate>
<ycoordinate>188</ycoordinate>
<xcoordinate2>145</xcoordinate2>
<ycoordinate2>249</ycoordinate2>
<entry>4</entry>
<exit>3</exit>
</bus>

<bus>
<number>14</number>
<name></name>
<bits>8</bits>
<xcoordinate>159</xcoordinate>
<ycoordinate>279</ycoordinate>
<xcoordinate2>159</xcoordinate2>
<ycoordinate2>301</ycoordinate2>
<entry>3</entry>
<exit>0</exit>
</bus>

<bus>
<number>15</number>
<name></name>
<bits>8</bits>
<xcoordinate>159</xcoordinate>
<ycoordinate>300</ycoordinate>
<xcoordinate2>91</xcoordinate2>
<ycoordinate2>300</ycoordinate2>
<entry>14</entry>
<exit>0</exit>
</bus>

<bus>
<number>16</number>
<name></name>
<bits>8</bits>
<xcoordinate>92</xcoordinate>
<ycoordinate>300</ycoordinate>
<xcoordinate2>92</xcoordinate2>
<ycoordinate2>81</ycoordinate2>
<entry>15</entry>
<exit>0</exit>
</bus>

<bus>
<number>17</number>
<name></name>
<bits>8</bits>
<xcoordinate>92</xcoordinate>
<ycoordinate>84</ycoordinate>
<xcoordinate2>179</xcoordinate2>
<ycoordinate2>84</ycoordinate2>
<entry>16</entry>
<exit>0</exit>
</bus>

<bus>
<number>18</number>
<name></name>
<bits>8</bits>
<xcoordinate>174</xcoordinate>
<ycoordinate>84</ycoordinate>
<xcoordinate2>174</xcoordinate2>
<ycoordinate2>129</ycoordinate2>
<entry>17</entry>
<exit>1</exit>
</bus>

<bus>
<number>19</number>
<name></name>
<bits>8</bits>
<xcoordinate>272</xcoordinate>
<ycoordinate>254</ycoordinate>
<xcoordinate2>272</xcoordinate2>
<ycoordinate2>284</ycoordinate2>
<entry>2</entry>
<exit>0</exit>
</bus>

<bus>
<number>20</number>
<name></name>
<bits>8</bits>
<xcoordinate>272</xcoordinate>
<ycoordinate>280</ycoordinate>
<xcoordinate2>397</xcoordinate2>
<ycoordinate2>280</ycoordinate2>
<entry>19</entry>
<exit>0</exit>
</bus>

<bus>
<number>21</number>
<name></name>
<bits>8</bits>
<xcoordinate>382</xcoordinate>
<ycoordinate>280</ycoordinate>
<xcoordinate2>382</xcoordinate2>
<ycoordinate2>320</ycoordinate2>
<entry>20</entry>
<exit>6</exit>
</bus>

<bus>
<number>22</number>
<name></name>
<bits>8</bits>
<xcoordinate>303</xcoordinate>
<ycoordinate>280</ycoordinate>
<xcoordinate2>303</xcoordinate2>
<ycoordinate2>318</ycoordinate2>
<entry>20</entry>
<exit>5</exit>
</bus>

<bus>
<number>23</number>
<name></name>
<bits>8</bits>
<xcoordinate>303</xcoordinate>
<ycoordinate>348</ycoordinate>
<xcoordinate2>303</xcoordinate2>
<ycoordinate2>371</ycoordinate2>
<entry>5</entry>
<exit>0</exit>
</bus>

<bus>
<number>24</number>
<name></name>
<bits>8</bits>
<xcoordinate>303</xcoordinate>
<ycoordinate>371</ycoordinate>
<xcoordinate2>323</xcoordinate2>
<ycoordinate2>371</ycoordinate2>
<entry>23</entry>
<exit>0</exit>
</bus>

<bus>
<number>25</number>
<name></name>
<bits>8</bits>
<xcoordinate>322</xcoordinate>
<ycoordinate>371</ycoordinate>
<xcoordinate2>322</xcoordinate2>
<ycoordinate2>393</ycoordinate2>
<entry>24</entry>
<exit>8</exit>
</bus>

<bus>
<number>26</number>
<name></name>
<bits>8</bits>
<xcoordinate>380</xcoordinate>
<ycoordinate>350</ycoordinate>
<xcoordinate2>380</xcoordinate2>
<ycoordinate2>372</ycoordinate2>
<entry>6</entry>
<exit>0</exit>
</bus>

<bus>
<number>27</number>
<name></name>
<bits>8</bits>
<xcoordinate>380</xcoordinate>
<ycoordinate>371</ycoordinate>
<xcoordinate2>344</xcoordinate2>
<ycoordinate2>371</ycoordinate2>
<entry>26</entry>
<exit>0</exit>
</bus>

<bus>
<number>28</number>
<name></name>
<bits>8</bits>
<xcoordinate>345</xcoordinate>
<ycoordinate>371</ycoordinate>
<xcoordinate2>345</xcoordinate2>
<ycoordinate2>393</ycoordinate2>
<entry>27</entry>
<exit>8</exit>
</bus>

<bus>
<number>29</number>
<name></name>
<bits>8</bits>
<xcoordinate>334</xcoordinate>
<ycoordinate>423</ycoordinate>
<xcoordinate2>334</xcoordinate2>
<ycoordinate2>469</ycoordinate2>
<entry>8</entry>
<exit>7</exit>
</bus>

<bus>
<number>30</number>
<name></name>
<bits>8</bits>
<xcoordinate>339</xcoordinate>
<ycoordinate>499</ycoordinate>
<xcoordinate2>339</xcoordinate2>
<ycoordinate2>522</ycoordinate2>
<entry>7</entry>
<exit>0</exit>
</bus>

<bus>
<number>31</number>
<name></name>
<bits>8</bits>
<xcoordinate>339</xcoordinate>
<ycoordinate>521</ycoordinate>
<xcoordinate2>426</xcoordinate2>
<ycoordinate2>521</ycoordinate2>
<entry>30</entry>
<exit>0</exit>
</bus>

<bus>
<number>32</number>
<name></name>
<bits>8</bits>
<xcoordinate>424</xcoordinate>
<ycoordinate>521</ycoordinate>
<xcoordinate2>424</xcoordinate2>
<ycoordinate2>186</ycoordinate2>
<entry>31</entry>
<exit>0</exit>
</bus>

<bus>
<number>33</number>
<name></name>
<bits>8</bits>
<xcoordinate>424</xcoordinate>
<ycoordinate>189</ycoordinate>
<xcoordinate2>270</xcoordinate2>
<ycoordinate2>189</ycoordinate2>
<entry>32</entry>
<exit>0</exit>
</bus>

<bus>
<number>34</number>
<name></name>
<bits>8</bits>
<xcoordinate>272</xcoordinate>
<ycoordinate>189</ycoordinate>
<xcoordinate2>272</xcoordinate2>
<ycoordinate2>224</ycoordinate2>
<entry>33</entry>
<exit>2</exit>
</bus>

</processor>

